Workbook

Sheet Moneda homogenea
A1: Nro | B1: Rubro | C1: 2019 | D1: 2020 | E1: 2021 | F1: 2022 | G1: 2023 | H1: 2024 | I1: 2025-Q1 | J1: 2025-H1 | K1: 2025-Q3 | L1: 2025 (ENE-SEP)
B2: UNIDAD DEL BALANCE ORIGINAL | C2: MILES | D2: MILES | E2: MILES | F2: MILES | G2: MILES | H2: MILLONES | I2: MILLONES | J2: MILLONES | K2: MILLONES | L2: MILLONES
B3: Ajuste de unidad - Expongo todo en MILLONES | C3: 0.001 | D3: 0.001 | E3: 0.001 | F3: 0.001 | G3: 0.001 | H3: 1 | I3: 1 | J3: 1 | K3: 1 | L3: 1
B4: ÍNDICE DE CIERRE - FACPCE | C4: =VLOOKUP(DATE(YEAR(C6),MONTH(C6),1),'ipc empalme ipim'!$A:$C,2,0) -> 283.4442 | D4: =VLOOKUP(DATE(YEAR(D6),MONTH(D6),1),'ipc empalme ipim'!$A:$C,2,0) -> 385.8826 | E4: =VLOOKUP(DATE(YEAR(E6),MONTH(E6),1),'ipc empalme ipim'!$A:$C,2,0) -> 582.4575 | F4: =VLOOKUP(DATE(YEAR(F6),MONTH(F6),1),'ipc empalme ipim'!$A:$C,2,0) -> 1134.5875 | G4: =VLOOKUP(DATE(YEAR(G6),MONTH(G6),1),'ipc empalme ipim'!$A:$C,2,0) -> 3533.1922 | H4: =VLOOKUP(DATE(YEAR(H6),MONTH(H6),1),'ipc empalme ipim'!$A:$C,2,0) -> 7694.0075 | I4: =VLOOKUP(DATE(YEAR(I6),MONTH(I6),1),'ipc empalme ipim'!$A:$C,2,0) -> 8353.3158 | J4: =VLOOKUP(DATE(YEAR(J6),MONTH(J6),1),'ipc empalme ipim'!$A:$C,2,0) -> 8855.5681 | ... L4: =VLOOKUP(DATE(YEAR(L6),MONTH(L6),1),'ipc empalme ipim'!$A:$C,2,0) -> 9384.0922
B5: AXI AL 30/09/2025 | C5: =$L$4/C4 -> 33.107371 | D5: =$L$4/D4 -> 24.318516 | E5: =$L$4/E4 -> 16.111205 | F5: =$L$4/F4 -> 8.2709286 | G5: =$L$4/G4 -> 2.6559812 | H5: =$L$4/H4 -> 1.2196625 | I5: =$L$4/I4 -> 1.1233973 | J5: =$L$4/J4 -> 1.0596827 | ... L5: =$L$4/L4 -> 1
B6: CIERRE | C6: 31/12/2019 | D6: 31/12/2020 | E6: 31/12/2021 | F6: 31/12/2022 | G6: 31/12/2023 | H6: 31/12/2024 | I6: 31/03/2025 | J6: 30/06/2025 | K6: 30/09/2025 | L6: 30/09/2025
A7: 1122500 | B7: EFECTIVO Y EQUIVALENTES A EFECTIVO | C7: ='Balances Originales'!C4*C$3*C$5 -> 329984.24 | D7: ='Balances Originales'!D4*D$3*D$5 -> 353732.25 | E7: ='Balances Originales'!E4*E$3*E$5 -> 312689.71 | F7: ='Balances Originales'!F4*F$3*F$5 -> 187675.75 | G7: ='Balances Originales'!G4*G$3*G$5 -> 249338.55 | H7: ='Balances Originales'!H4*H$3*H$5 -> 229613.66 | I7: ='Balances Originales'!I4*I$3*I$5 -> 238269.19 | J7: ='Balances Originales'!J4*J$3*J$5 -> 244589.6 | ... L7: ='Balances Originales'!L4*L$3*L$5 -> 299173
A8: 1122300 | B8: ACTIVOS FINANCIEROS CORRIENTES | C8: ='Balances Originales'!C5*C$3*C$5 -> 424.40338 | D8: ='Balances Originales'!D5*D$3*D$5 -> 6565.9993 | E8: ='Balances Originales'!E5*E$3*E$5 -> 8765.7522 | F8: ='Balances Originales'!F5*F$3*F$5 -> 16870.089 | G8: ='Balances Originales'!G5*G$3*G$5 -> 0 | H8: ='Balances Originales'!H5*H$3*H$5 -> 78269.4 | I8: ='Balances Originales'!I5*I$3*I$5 -> 83126.905 | J8: ='Balances Originales'!J5*J$3*J$5 -> 81789.489 | ... L8: ='Balances Originales'!L5*L$3*L$5 -> 115489
A9: 1121999 | B9: CUENTAS POR COBRAR CORRIENTES | C9: ='Balances Originales'!C6*C$3*C$5 -> 774561.21 | D9: ='Balances Originales'!D6*D$3*D$5 -> 768274.13 | E9: ='Balances Originales'!E6*E$3*E$5 -> 878584.9 | F9: ='Balances Originales'!F6*F$3*F$5 -> 865375.69 | G9: ='Balances Originales'!G6*G$3*G$5 -> 1011386.9 | H9: ='Balances Originales'!H6*H$3*H$5 -> 722017.01 | I9: ='Balances Originales'!I6*I$3*I$5 -> 827860.66 | J9: ='Balances Originales'!J6*J$3*J$5 -> 819942.2 | ... L9: ='Balances Originales'!L6*L$3*L$5 -> 852853
A10: 1122400 | B10: OTROS ACTIVOS NO FINANCIEROS CORRIENTES | C10: ='Balances Originales'!C7*C$3*C$5 -> 14460.968 | D10: ='Balances Originales'!D7*D$3*D$5 -> 17572.827 | E10: ='Balances Originales'!E7*E$3*E$5 -> 28972.941 | F10: ='Balances Originales'!F7*F$3*F$5 -> 23660.836 | G10: ='Balances Originales'!G7*G$3*G$5 -> 244708.54 | H10: ='Balances Originales'!H7*H$3*H$5 -> 207037.7 | I10: ='Balances Originales'!I7*I$3*I$5 -> 213339.88 | J10: ='Balances Originales'!J7*J$3*J$5 -> 205161.99 | ... L10: ='Balances Originales'!L7*L$3*L$5 -> 223489
A11: 1120100 | B11: INVENTARIOS CORRIENTES | C11: ='Balances Originales'!C8*C$3*C$5 -> 719764.83 | D11: ='Balances Originales'!D8*D$3*D$5 -> 762635.06 | E11: ='Balances Originales'!E8*E$3*E$5 -> 892696.04 | F11: ='Balances Originales'!F8*F$3*F$5 -> 1040277.3 | G11: ='Balances Originales'!G8*G$3*G$5 -> 1142730.5 | H11: ='Balances Originales'!H8*H$3*H$5 -> 991647.79 | I11: ='Balances Originales'!I8*I$3*I$5 -> 976770.34 | J11: ='Balances Originales'!J8*J$3*J$5 -> 1026985.1 | ... L11: ='Balances Originales'!L8*L$3*L$5 -> 1046192
A12: 1139999 | B12: ACTIVO CORRIENTE | C12: ='Balances Originales'!C9*C$3*C$5 -> 1839195.7 | D12: ='Balances Originales'!D9*D$3*D$5 -> 1908780.3 | E12: ='Balances Originales'!E9*E$3*E$5 -> 2121709.4 | F12: ='Balances Originales'!F9*F$3*F$5 -> 2133859.7 | G12: ='Balances Originales'!G9*G$3*G$5 -> 2648164.4 | H12: ='Balances Originales'!H9*H$3*H$5 -> 2228585.6 | I12: ='Balances Originales'!I9*I$3*I$5 -> 2339367 | J12: ='Balances Originales'!J9*J$3*J$5 -> 2378468.4 | ... L12: ='Balances Originales'!L9*L$3*L$5 -> 2537196
A13: 1112400 | B13: ACTIVOS FINANCIEROS NO CORRIENTES | C13: ='Balances Originales'!C10*C$3*C$5 -> 0 | D13: ='Balances Originales'!D10*D$3*D$5 -> 0 | E13: ='Balances Originales'!E10*E$3*E$5 -> 0 | F13: ='Balances Originales'!F10*F$3*F$5 -> 0 | G13: ='Balances Originales'!G10*G$3*G$5 -> 68130.864 | H13: ='Balances Originales'!H10*H$3*H$5 -> 0 | I13: ='Balances Originales'!I10*I$3*I$5 -> 0 | J13: ='Balances Originales'!J10*J$3*J$5 -> 0 | ... L13: ='Balances Originales'!L10*L$3*L$5 -> 0
A14: 1111999 | B14: CUENTAS POR COBRAR NO CORRIENTES | C14: ='Balances Originales'!C11*C$3*C$5 -> 66925.656 | D14: ='Balances Originales'!D11*D$3*D$5 -> 69830.886 | E14: ='Balances Originales'!E11*E$3*E$5 -> 85524.382 | F14: ='Balances Originales'!F11*F$3*F$5 -> 56820.543 | G14: ='Balances Originales'!G11*G$3*G$5 -> 87926.299 | H14: ='Balances Originales'!H11*H$3*H$5 -> 49426.822 | I14: ='Balances Originales'!I11*I$3*I$5 -> 57588.714 | J14: ='Balances Originales'!J11*J$3*J$5 -> 69542.736 | ... L14: ='Balances Originales'!L11*L$3*L$5 -> 55038
A15: 1110100 | B15: PROPIEDADES PLANTAS Y EQUIPOS | C15: ='Balances Originales'!C12*C$3*C$5 -> 1196949.9 | D15: ='Balances Originales'!D12*D$3*D$5 -> 1151286 | E15: ='Balances Originales'!E12*E$3*E$5 -> 1112783.8 | F15: ='Balances Originales'!F12*F$3*F$5 -> 1068670.4 | G15: ='Balances Originales'!G12*G$3*G$5 -> 1190756.1 | H15: ='Balances Originales'!H12*H$3*H$5 -> 1062981 | I15: ='Balances Originales'!I12*I$3*I$5 -> 1058598.6 | J15: ='Balances Originales'!J12*J$3*J$5 -> 1102631.6 | ... L15: ='Balances Originales'!L12*L$3*L$5 -> 1179900
A16: 1112500 | B16: OTROS ACTIVOS NO FINANCIEROS NO CORRIENTES | C16: ='Balances Originales'!C13*C$3*C$5 -> 375240 | D16: ='Balances Originales'!D13*D$3*D$5 -> 339405.65 | E16: ='Balances Originales'!E13*E$3*E$5 -> 323508.84 | F16: ='Balances Originales'!F13*F$3*F$5 -> 288511.19 | G16: ='Balances Originales'!G13*G$3*G$5 -> 305039.36 | H16: ='Balances Originales'!H13*H$3*H$5 -> 233851.98 | I16: ='Balances Originales'!I13*I$3*I$5 -> 221139.63 | J16: ='Balances Originales'!J13*J$3*J$5 -> 227768.2 | ... L16: ='Balances Originales'!L13*L$3*L$5 -> 241236
A17: 1110200 | B17: ACTIVOS INTANGIBLES | C17: ='Balances Originales'!C14*C$3*C$5 -> 199061.84 | D17: ='Balances Originales'!D14*D$3*D$5 -> 195714.2 | E17: ='Balances Originales'!E14*E$3*E$5 -> 195273.48 | F17: ='Balances Originales'!F14*F$3*F$5 -> 196525.23 | G17: ='Balances Originales'!G14*G$3*G$5 -> 198212.99 | H17: ='Balances Originales'!H14*H$3*H$5 -> 191211.36 | I17: ='Balances Originales'!I14*I$3*I$5 -> 189139.66 | J17: ='Balances Originales'!J14*J$3*J$5 -> 192709.65 | ... L17: ='Balances Originales'!L14*L$3*L$5 -> 200346
A18: 1119999 | B18: ACTIVO NO CORRIENTE | C18: ='Balances Originales'!C15*C$3*C$5 -> 1838177.4 | D18: ='Balances Originales'!D15*D$3*D$5 -> 1756236.8 | E18: ='Balances Originales'!E15*E$3*E$5 -> 1717090.5 | F18: ='Balances Originales'!F15*F$3*F$5 -> 1610527.3 | G18: ='Balances Originales'!G15*G$3*G$5 -> 1850065.6 | H18: ='Balances Originales'!H15*H$3*H$5 -> 1537471.1 | I18: ='Balances Originales'!I15*I$3*I$5 -> 1526466.6 | J18: ='Balances Originales'!J15*J$3*J$5 -> 1592652.2 | ... L18: ='Balances Originales'!L15*L$3*L$5 -> 1676520
A19: 1999999 | B19: TOTAL DEL ACTIVO | C19: ='Balances Originales'!C16*C$3*C$5 -> 3677373.1 | D19: ='Balances Originales'!D16*D$3*D$5 -> 3665017 | E19: ='Balances Originales'!E16*E$3*E$5 -> 3838799.8 | F19: ='Balances Originales'!F16*F$3*F$5 -> 3744387 | G19: ='Balances Originales'!G16*G$3*G$5 -> 4498230.1 | H19: ='Balances Originales'!H16*H$3*H$5 -> 3766056.7 | I19: ='Balances Originales'!I16*I$3*I$5 -> 3865833.6 | J19: ='Balances Originales'!J16*J$3*J$5 -> 3971120.6 | ... L19: ='Balances Originales'!L16*L$3*L$5 -> 4213716
A20: 2210999 | B20: CAPITAL | C20: ='Balances Originales'!C17*C$3*1 -> 700 | D20: ='Balances Originales'!D17*D$3*1 -> 700 | E20: ='Balances Originales'!E17*E$3*1 -> 700 | F20: ='Balances Originales'!F17*F$3*1 -> 700 | G20: ='Balances Originales'!G17*G$3*1 -> 700 | H20: ='Balances Originales'!H17*H$3*1 -> 700 | I20: ='Balances Originales'!I17*I$3*1 -> 700 | J20: ='Balances Originales'!J17*J$3*1 -> 700 | ... L20: ='Balances Originales'!L17*L$3*1 -> 700
A21: 2210300 | B21: AJUSTE DE CAPITAL | C21: =(('Balances Originales'!C18+'Balances Originales'!C17)*C$3*C$5)-C20 -> 179845.38 | D21: =(('Balances Originales'!D18+'Balances Originales'!D17)*D$3*D$5)-D20 -> 179845.38 | E21: =(('Balances Originales'!E18+'Balances Originales'!E17)*E$3*E$5)-E20 -> 179845.37 | F21: =(('Balances Originales'!F18+'Balances Originales'!F17)*F$3*F$5)-F20 -> 179845.38 | G21: =(('Balances Originales'!G18+'Balances Originales'!G17)*G$3*G$5)-G20 -> 179845.37 | H21: =(('Balances Originales'!H18+'Balances Originales'!H17)*H$3*H$5)-H20 -> 179845.42 | I21: =(('Balances Originales'!I18+'Balances Originales'!I17)*I$3*I$5)-I20 -> 177531.47 | J21: =(('Balances Originales'!J18+'Balances Originales'!J17)*J$3*J$5)-J20 -> 180344.67 | ... L21: =(('Balances Originales'!L18+'Balances Originales'!L17)*L$3*L$5)-L20 -> 181700
A22: 2210500 | B22: APORTES NO CAPITALIZADOS O CONTRIBUCIONES DE CAPITAL | C22: ='Balances Originales'!C19*C$3*C$5 -> 0 | D22: ='Balances Originales'!D19*D$3*D$5 -> 0 | E22: ='Balances Originales'!E19*E$3*E$5 -> 0 | F22: ='Balances Originales'!F19*F$3*F$5 -> 0 | G22: ='Balances Originales'!G19*G$3*G$5 -> 0 | H22: ='Balances Originales'!H19*H$3*H$5 -> 0 | I22: ='Balances Originales'!I19*I$3*I$5 -> 0 | J22: ='Balances Originales'!J19*J$3*J$5 -> 0 | ... L22: ='Balances Originales'!L19*L$3*L$5 -> 0
A23: 2210900 | B23: OTROS CONCEPTOS DEL CAPITAL | C23: ='Balances Originales'!C20*C$3*C$5 -> -39.728845 | D23: ='Balances Originales'!D20*D$3*D$5 -> -39.736455 | E23: ='Balances Originales'!E20*E$3*E$5 -> -39.730232 | F23: ='Balances Originales'!F20*F$3*F$5 -> -39.733541 | G23: ='Balances Originales'!G20*G$3*G$5 -> -39.725511 | H23: ='Balances Originales'!H20*H$3*H$5 -> -40.248862 | I23: ='Balances Originales'!I20*I$3*I$5 -> -39.318905 | J23: ='Balances Originales'!J20*J$3*J$5 -> -40.267942 | ... L23: ='Balances Originales'!L20*L$3*L$5 -> -40
A24: 2211100 | B24: RESERVA LEGAL | C24: ='Balances Originales'!C21*C$3*C$5 -> 36109.084 | D24: ='Balances Originales'!D21*D$3*D$5 -> 36109.081 | E24: ='Balances Originales'!E21*E$3*E$5 -> 36109.077 | F24: ='Balances Originales'!F21*F$3*F$5 -> 36109.079 | G24: ='Balances Originales'!G21*G$3*G$5 -> 36109.074 | H24: ='Balances Originales'!H21*H$3*H$5 -> 36108.107 | I24: ='Balances Originales'!I21*I$3*I$5 -> 35646.519 | J24: ='Balances Originales'!J21*J$3*J$5 -> 36209.357 | ... L24: ='Balances Originales'!L21*L$3*L$5 -> 36480
A25: 2211200 | B25: OTRAS RESERVAS | C25: ='Balances Originales'!C22*C$3*C$5 -> 442431.77 | D25: ='Balances Originales'!D22*D$3*D$5 -> 334803.69 | E25: ='Balances Originales'!E22*E$3*E$5 -> 326853.24 | F25: ='Balances Originales'!F22*F$3*F$5 -> 524676.82 | G25: ='Balances Originales'!G22*G$3*G$5 -> 636956.04 | H25: ='Balances Originales'!H22*H$3*H$5 -> 615735.62 | I25: ='Balances Originales'!I22*I$3*I$5 -> 607845.55 | J25: ='Balances Originales'!J22*J$3*J$5 -> 946347.5 | ... L25: ='Balances Originales'!L22*L$3*L$5 -> 953432
A26: 2211300 | B26: INTERESES NO CONTROLANTES | C26: ='Balances Originales'!C23*C$3*C$5 -> 357222.44 | D26: ='Balances Originales'!D23*D$3*D$5 -> 382538.55 | E26: ='Balances Originales'!E23*E$3*E$5 -> 484476.5 | F26: ='Balances Originales'!F23*F$3*F$5 -> 499258.36 | G26: ='Balances Originales'!G23*G$3*G$5 -> 600972.7 | H26: ='Balances Originales'!H23*H$3*H$5 -> 531721.61 | I26: ='Balances Originales'!I23*I$3*I$5 -> 531034.39 | J26: ='Balances Originales'!J23*J$3*J$5 -> 554423.86 | ... L26: ='Balances Originales'!L23*L$3*L$5 -> 592076
A27: 2212999 | B27: RESULTADOS NO ASIGNADOS | C27: ='Balances Originales'!C24*C$3*C$5 -> -56120.139 | D27: ='Balances Originales'!D24*D$3*D$5 -> 102715.77 | E27: ='Balances Originales'!E24*E$3*E$5 -> 294987.98 | F27: ='Balances Originales'!F24*F$3*F$5 -> 260732.21 | G27: ='Balances Originales'!G24*G$3*G$5 -> 4180.0444 | H27: ='Balances Originales'!H24*H$3*H$5 -> 364914.47 | I27: ='Balances Originales'!I24*I$3*I$5 -> 394904.47 | J27: ='Balances Originales'!J24*J$3*J$5 -> 30859.02 | ... L27: ='Balances Originales'!L24*L$3*L$5 -> 40374
A28: 2213999 | B28: RESULTADOS INTEGRALES | C28: ='Balances Originales'!C25*C$3*C$5 -> 30107.744 | D28: ='Balances Originales'!D25*D$3*D$5 -> 26208.284 | E28: ='Balances Originales'!E25*E$3*E$5 -> -149146.77 | F28: ='Balances Originales'!F25*F$3*F$5 -> -201596.04 | G28: ='Balances Originales'!G25*G$3*G$5 -> 36659.59 | H28: ='Balances Originales'!H25*H$3*H$5 -> -332882.48 | I28: ='Balances Originales'!I25*I$3*I$5 -> -330264.19 | J28: ='Balances Originales'!J25*J$3*J$5 -> -304720.23 | ... L28: ='Balances Originales'!L25*L$3*L$5 -> -274005
A29: 2299999 | B29: TOTAL PATRIMONIO NETO | C29: ='Balances Originales'!C26*C$3*C$5 -> 990256.55 | D29: ='Balances Originales'!D26*D$3*D$5 -> 1062881 | E29: ='Balances Originales'!E26*E$3*E$5 -> 1173785.7 | F29: ='Balances Originales'!F26*F$3*F$5 -> 1299686.1 | G29: ='Balances Originales'!G26*G$3*G$5 -> 1495383.1 | H29: ='Balances Originales'!H26*H$3*H$5 -> 1396102.5 | I29: ='Balances Originales'!I26*I$3*I$5 -> 1417358.9 | J29: ='Balances Originales'!J26*J$3*J$5 -> 1444123.9 | ... L29: ='Balances Originales'!L26*L$3*L$5 -> 1530717
A30: 2322200 | B30: PASIVOS FINANCIEROS CORRIENTES | C30: ='Balances Originales'!C27*C$3*C$5 -> 545079.92 | D30: ='Balances Originales'!D27*D$3*D$5 -> 388270.57 | E30: ='Balances Originales'!E27*E$3*E$5 -> 418455.35 | F30: ='Balances Originales'!F27*F$3*F$5 -> 562577.22 | G30: ='Balances Originales'!G27*G$3*G$5 -> 548070.97 | H30: ='Balances Originales'!H27*H$3*H$5 -> 808550.84 | I30: ='Balances Originales'!I27*I$3*I$5 -> 921618.27 | J30: ='Balances Originales'!J27*J$3*J$5 -> 922370.06 | ... L30: ='Balances Originales'!L27*L$3*L$5 -> 653562
A31: 2321999 | B31: CUENTAS POR PAGAR CORRIENTES | C31: ='Balances Originales'!C28*C$3*C$5 -> 695733.95 | D31: ='Balances Originales'!D28*D$3*D$5 -> 785737.7 | E31: ='Balances Originales'!E28*E$3*E$5 -> 885617.04 | F31: ='Balances Originales'!F28*F$3*F$5 -> 1072234.7 | G31: ='Balances Originales'!G28*G$3*G$5 -> 1300400 | H31: ='Balances Originales'!H28*H$3*H$5 -> 831034.1 | I31: ='Balances Originales'!I28*I$3*I$5 -> 845146.37 | J31: ='Balances Originales'!J28*J$3*J$5 -> 886834.66 | ... L31: ='Balances Originales'!L28*L$3*L$5 -> 942558
A32: 2322100 | B32: PASIVOS POR IMPUESTOS CORRIENTES | C32: ='Balances Originales'!C29*C$3*C$5 -> 24270.418 | D32: ='Balances Originales'!D29*D$3*D$5 -> 16661.004 | E32: ='Balances Originales'!E29*E$3*E$5 -> 26541.825 | F32: ='Balances Originales'!F29*F$3*F$5 -> 11121.909 | G32: ='Balances Originales'!G29*G$3*G$5 -> 15779.774 | H32: ='Balances Originales'!H29*H$3*H$5 -> 132776.12 | I32: ='Balances Originales'!I29*I$3*I$5 -> 120575.35 | J32: ='Balances Originales'!J29*J$3*J$5 -> 52976.717 | ... L32: ='Balances Originales'!L29*L$3*L$5 -> 65192
A33: 2322300 | B33: OTROS PASIVOS NO FINANCIEROS CORRIENTES | C33: ='Balances Originales'!C30*C$3*C$5 -> 25710.555 | D33: ='Balances Originales'!D30*D$3*D$5 -> 32913.579 | E33: ='Balances Originales'!E30*E$3*E$5 -> 37028.302 | F33: ='Balances Originales'!F30*F$3*F$5 -> 27148.678 | G33: ='Balances Originales'!G30*G$3*G$5 -> 25901.955 | H33: ='Balances Originales'!H30*H$3*H$5 -> 22858.914 | I33: ='Balances Originales'!I30*I$3*I$5 -> 17574.427 | J33: ='Balances Originales'!J30*J$3*J$5 -> 18413.046 | ... L33: ='Balances Originales'!L30*L$3*L$5 -> 18849
... A72: 8000005 | B72: CAPITAL DE TRABAJO | C72: ='Balances Originales'!C69*C$3*C$5 -> 548400.82 | D72: ='Balances Originales'!D69*D$3*D$5 -> 685197.41 | E72: ='Balances Originales'!E69*E$3*E$5 -> 754066.84 | F72: ='Balances Originales'!F69*F$3*F$5 -> 460777.18 | G72: ='Balances Originales'!G69*G$3*G$5 -> 758011.79 | H72: ='Balances Originales'!H69*H$3*H$5 -> 433365.59 | I72: ='Balances Originales'!I69*I$3*I$5 -> 434452.55 | J72: ='Balances Originales'!J69*J$3*J$5 -> 497873.9 | ... L72: ='Balances Originales'!L69*L$3*L$5 -> 857035
B73: INDICADORES
B74: VARIACIÓN % VENTAS | C74: - | D74: =(D42-C42)/C42 -> -0.034808761 | E74: =(E42-D42)/D42 -> 0.12726081 | F74: =(F42-E42)/E42 -> 0.065438657 | G74: =(G42-F42)/F42 -> -0.016092295 | H74: =(H42-G42)/G42 -> -0.055390619 | I74: =(I42-H42)/H42 -> -0.76585772 | J74: =(J42-I42)/I42 -> 1.0174241 | K74: =(K42-J42)/J42 -> 0.54621399 | L74: =(L42-K42)/K42 -> 0.61031573
B75: VARIACIÓN % UTILIDAD BRUTA | C75: - | D75: =(D44-C44)/C44 -> 0.096148017 | E75: =(E44-D44)/D44 -> 0.002395752 | F75: =(F44-E44)/E44 -> 0.069867239 | G75: =(G44-F44)/F44 -> -0.057027776 | H75: =(H44-G44)/G44 -> -0.027801135 | I75: =(I44-H44)/H44 -> -0.75783274 | J75: =(J44-I44)/I44 -> 0.94803398 | K75: =(K44-J44)/J44 -> 0.58032951 | L75: =(L44-K44)/K44 -> 0.59714048
B76: ROTACIÓN DE PASIVOS | C76: =C42/C40 -> 1.6597345 | D76: =D42/D40 -> 1.654278 | E76: =E42/E40 -> 1.8208048 | F76: =F42/F40 -> 2.114782 | G76: =G42/G40 -> 1.6939965 | H76: =H42/H40 -> 2.0274867 | I76: =I42/I40 -> 0.45949649 | J76: =J42/J40 -> 0.89819443 | ... L76: =L42/L40 -> 2.1063724
B77: MARGEN BRUTO | C77: =C44/C42 -> 0.28952659 | D77: =D44/D42 -> 0.32880945 | E77: =E44/E42 -> 0.2923877 | F77: =F44/F42 -> 0.29360303 | G77: =G44/G42 -> 0.28138768 | H77: =H44/H42 -> 0.28960625 | I77: =I44/I42 -> 0.29953219 | J77: =J44/J42 -> 0.28922966 | ... L77: =L44/L42 -> 0.29319257
B78: LIQUIDEZ (AC / PC) | C78: =C12/C34 -> 1.4248551 | D78: =D12/D34 -> 1.5599927 | E78: =E12/E34 -> 1.5513625 | F78: =F12/F34 -> 1.2754061 | G78: =G12/G34 -> 1.401032 | H78: =H12/H34 -> 1.2413997 | I78: =I12/I34 -> 1.2280693 | J78: =J12/J34 -> 1.2647428 | ... L78: =L12/L34 -> 1.510091
B79: SOLVENCIA (PN / PAS) | C79: =C29/C40 -> 0.36852014 | D79: =D29/D40 -> 0.40846482 | E79: =E29/E40 -> 0.44044256 | F79: =F29/F40 -> 0.53163398 | G79: =G29/G40 -> 0.49798845 | H79: =H29/H40 -> 0.58908417 | I79: =I29/I40 -> 0.57887422 | J79: =J29/J40 -> 0.57147835 | ... L79: =L29/L40 -> 0.57052463
B80: INMOVILIZACIÓN DEL CAPITAL (ANC / TA) | C80: =C18/C19 -> 0.49986156 | D80: =D18/D19 -> 0.47918925 | E80: =E18/E19 -> 0.44729878 | F80: =F18/F19 -> 0.43011776 | G80: =G18/G19 -> 0.41128746 | H80: =H18/H19 -> 0.40824429 | I80: =I18/I19 -> 0.39486092 | J80: =J18/J19 -> 0.40105864 | ... L80: =L18/L19 -> 0.39787209
B81: RENTABILIDAD PATRIMONIO NETO - ROI | C81: =C60/C29 -> -0.0048173789 | D81: =D60/D29 -> 0.12450808 | E81: =E60/E29 -> 0.27339694 | F81: =F60/F29 -> 0.22515323 | G81: =G60/G29 -> 0.046271238 | H81: =H60/H29 -> 0.2699004 | I81: =I60/I29 -> 0.037734847 | J81: =J60/J29 -> 0.042987579 | ... L81: =L60/L29 -> 0.10214494
B82: RENTABILIDAD DEL ACTIVO - ROA | C82: =C60/C19 -> -0.0012972415 | D82: =D60/D19 -> 0.03610823 | E82: =E60/E19 -> 0.083596287 | F82: =F60/F19 -> 0.078151247 | G82: =G60/G19 -> 0.015382323 | H82: =H60/H19 -> 0.10005389 | I82: =I60/I19 -> 0.013835003 | J82: =J60/J19 -> 0.015632714 | ... L82: =L60/L19 -> 0.037106203
B83: ENDEUDAMIENTO (PAS / PN) | C83: =C40/C29 -> 2.7135559 | D83: =D40/D29 -> 2.4481913 | E83: =E40/E29 -> 2.2704436 | F83: =F40/F29 -> 1.8809934 | G83: =G40/G29 -> 2.0080787 | H83: =H40/H29 -> 1.6975503 | I83: =I40/I29 -> 1.727491 | J83: =J40/J29 -> 1.7498476 | ... L83: =L40/L29 -> 1.7527727
B84: ENDEUDAMIENTO A CORTO PLAZO (PC / PN) | C84: =C34/C29 -> 1.3034954 | D84: =D34/D29 -> 1.1511946 | E84: =E34/E29 -> 1.1651552 | F84: =F34/F29 -> 1.2872974 | G84: =G34/G29 -> 1.2639923 | H84: =H34/H29 -> 1.2858798 | I84: =I34/I29 -> 1.3439888 | J84: =J34/J29 -> 1.302239 | ... L84: =L34/L29 -> 1.0976301
B85: APALANCAMIENTO | C85: =C82/(C53/-C40) -> -0.022573286 | D85: =D82/(D53/-D40) -> 0.70095948 | E85: =E82/(E53/-E40) -> 5.4034004 | F85: =F82/(F53/-F40) -> 97.307606 | G85: =G82/(G53/-G40) -> -0.23791531 | H85: =H82/(H53/-H40) -> 2.5774837 | I85: =I82/(I53/-I40) -> 1.0927256 | J85: =J82/(J53/-J40) -> 0.5802165 | ... L85: =L82/(L53/-L40) -> 0.61337645
B86: MARGEN NETO / VENTAS | C86: =C60/C42 -> -0.0010696296 | D86: =D60/D42 -> 0.030742821 | E86: =E60/E42 -> 0.066133203 | F86: =F60/F42 -> 0.056601155 | G86: =G60/G42 -> 0.013602473 | H86: =H60/H42 -> 0.078419283 | I86: =I60/I42 -> 0.047538405 | J86: =J60/J42 -> 0.02735095 | ... L86: =L60/L42 -> 0.02766662
B87: DEUDA FINANCIERA / EBITDA | C87: =(C30+C35)/C71 -> 4.9126673 | D87: =(D30+D35)/D71 -> 2.7454669 | E87: =(E30+E35)/E71 -> 2.8298891 | F87: =(F30+F35)/F71 -> 2.179421 | G87: =(G30+G35)/G71 -> 3.0932396 | H87: =(H30+H35)/H71 -> 2.897412 | I87: =(I30+I35)/I71 -> 10.579544 | J87: =(J30+J35)/J71 -> 6.816594 | ... L87: =(L30+L35)/L71 -> 2.7886081
B88: EBITDA / COSTOS FINANCIEROS | C88: =C71/C53 -> -2.3687313 | D88: =D71/D53 -> -4.2128923 | E88: =E71/E53 -> -11.785624 | F88: =F71/F53 -> -248.57256 | G88: =G71/G53 -> 2.3004495 | H88: =H71/H53 -> -4.2206345 | I88: =I71/I53 -> -3.6336296 | J88: =J71/J53 -> -2.7343574 | ... L88: =L71/L53 -> -3.0409175
B89: ANÁLISIS DU-PONT (ROE) | C89: =C60/C29 -> -0.0048173789 | D89: =D60/D29 -> 0.12450808 | E89: =E60/E29 -> 0.27339694 | F89: =F60/F29 -> 0.22515323 | G89: =G60/G29 -> 0.046271238 | H89: =H60/H29 -> 0.2699004 | I89: =I60/I29 -> 0.037734847 | J89: =J60/J29 -> 0.042987579 | ... L89: =L60/L29 -> 0.10214494
B90: PRUEBA ÁCIDA ((AC-INV)/PC) | C90: =(C12-C11)/C34 -> 0.86724148 | D90: =(D12-D11)/D34 -> 0.93671238 | E90: =(E12-E11)/E34 -> 0.89863638 | F90: =(F12-F11)/F34 -> 0.65363326 | G90: =(G12-G11)/G34 -> 0.79646157 | H90: =(H12-H11)/H34 -> 0.68901739 | I90: =(I12-I11)/I34 -> 0.71530596 | J90: =(J12-J11)/J34 -> 0.71864683 | ... L90: =(L12-L11)/L34 -> 0.88741734
B91: COBERTURA DE GASTOS FINANCIEROS | C91: =C70/C53 -> -1.404215 | D91: =D70/D53 -> -3.294946 | E91: =E70/E53 -> -8.6152011 | F91: =F70/F53 -> -178.73005 | G91: =G70/G53 -> 1.4798193 | H91: =H70/H53 -> -2.7741452 | I91: =I70/I53 -> -2.8978076 | J91: =J70/J53 -> -1.9812918 | ... L91: =L70/L53 -> -2.2480223
B92: ROTACIÓN DE ACTIVOS (VENTAS / TA) | C92: =C42/C19 -> 1.2127951 | D92: =D42/D19 -> 1.1745256 | E92: =E42/E19 -> 1.2640593 | F92: =F42/F19 -> 1.3807359 | G92: =G42/G19 -> 1.1308475 | H92: =H42/H19 -> 1.2758838 | I92: =I42/I19 -> 0.29102792 | J92: =J42/J19 -> 0.57156017 | ... L92: =L42/L19 -> 1.3411903
B93: CAPITAL DE TRABAJO (AC - PC) | C93: =C12-C34 -> 548400.82 | D93: =D12-D34 -> 685197.41 | E93: =E12-E34 -> 754066.84 | F93: =F12-F34 -> 460777.18 | G93: =G12-G34 -> 758011.79 | H93: =H12-H34 -> 433365.59 | I93: =I12-I34 -> 434452.55 | J93: =J12-J34 -> 497873.9 | ... L93: =L12-L34 -> 857035
B94: INDEC - VENTAS SUPERMERCADOS (PRECIOS CONSTANTES) | C94: -0.098 | D94: 0.008 | E94: 0.015 | F94: 0.016 | G94: 0.009 | H94: -0.11
B95: DIFERENCIA ARCOR vs INDEC (VAR% VENTAS - INDEC) | C95: =IFERROR(NA(),"") | D95: =D74-D94 -> -0.042808761 | E95: =E74-E94 -> 0.11226081 | F95: =F74-F94 -> 0.049438657 | G95: =G74-G94 -> -0.025092295 | H95: =H74-H94 -> 0.054609381
B96: MARGEN EBITDA (EBITDA / VENTAS) | C96: =C71/C42 -> 0.082016881 | D96: =D71/D42 -> 0.13118529 | E96: =E71/E42 -> 0.10014034 | F96: =F71/F42 -> 0.094401024 | G96: =G71/G42 -> 0.087801055 | H96: =H71/H42 -> 0.080808639 | I96: =I71/I42 -> 0.10012133 | J96: =J71/J42 -> 0.082021784 | ... L96: =L71/L42 -> 0.087335115
B97: DEUDA NETA / EBITDA | C97: =(C30+C35-C7)/C71 -> 4.0105462 | D97: =(D30+D35-D7)/D71 -> 2.1190679 | E97: =(E30+E35-E7)/E71 -> 2.1863993 | F97: =(F30+F35-F7)/F71 -> 1.7948823 | G97: =(G30+G35-G7)/G71 -> 2.53497 | H97: =(H30+H35-H7)/H71 -> 2.3060656 | I97: =(I30+I35-I7)/I71 -> 8.4642856 | J97: =(J30+J35-J7)/J71 -> 5.5027804 | ... L97: =(L30+L35-L7)/L71 -> 2.1824613
B98: % DEUDA FINANCIERA A LARGO PLAZO | C98: =C35/(C30+C35) -> 0.69667063 | D98: =D35/(D30+D35) -> 0.74956523 | E98: =E35/(E30+E35) -> 0.69569593 | F98: =F35/(F30+F35) -> 0.47110075 | G98: =G35/(G30+G35) -> 0.60328576 | H98: =H35/(H30+H35) -> 0.28131047 | I98: =I35/(I30+I35) -> 0.22664358 | J98: =J35/(J30+J35) -> 0.27316885 | ... L98: =L35/(L30+L35) -> 0.52515185
B99: OPERATING CASH FLOW RATIO (OCF / Pasivo Corriente) | C99: =C63/C34 -> 0.33615499 | D99: =D63/D34 -> 0.43132613 | E99: =E63/E34 -> 0.20468282 | F99: =F63/F34 -> 0.25461322 | G99: =G63/G34 -> 0.29406175 | H99: =H63/H34 -> 0.14579329 | I99: =I63/I34 -> 0.015579065 | J99: =J63/J34 -> 0.054777855 | ... L99: =L63/L34 -> 0.19865358
B100: RAZÓN DE GENERACIÓN PROPIA DE EFECTIVO (OPERAT / OPERATIVAS+ FINANCIACION) | C100: =C63/(C63+C65) -> 2.0217027 | D100: =D63/(D63+D65) -> 5.6504376 | E100: =E63/(E63+E65) -> 2.2419032 | F100: =F63/(F63+F65) -> 12.480191 | G100: =G63/(G63+G65) -> 1.6526602 | H100: =H63/(H63+H65) -> 0.85325249 | I100: =I63/(I63+I65) -> 0.45945006 | J100: =J63/(J63+J65) -> 1.284527 | ... L100: =L63/(L63+L65) -> 1.4182399
B101: RAZÓN DE GENERACIÓN DE EFECTIVO SOBRE VENTAS | C101: =C63/C42 -> 0.097290774 | D101: =D63/D42 -> 0.12260288 | E101: =E63/E42 -> 0.057688745 | F101: =F63/F42 -> 0.082396156 | G101: =G63/G42 -> 0.10926717 | H101: =H63/H42 -> 0.054469984 | I101: =I63/I42 -> 0.026377829 | J101: =J63/J42 -> 0.045386339 | ... L101: =L63/L42 -> 0.059059754

Sheet Balances Originales
A1: Nro | B1: Rubro | C1: 2019 | D1: 2020 | E1: 2021 | F1: 2022 | G1: 2023 | H1: 2024 | I1: 2025-Q1 | J1: 2025-H1 | K1: 2025-Q3 | L1: 2025 (ENE-SEP)
B2: UNIDAD | C2: MILES | D2: MILES | E2: MILES | F2: MILES | G2: MILES | H2: MILLONES | I2: MILLONES | J2: MILLONES | K2: MILLONES | L2: MILLONES
B3: CIERRE | C3: 31/12/2019 | D3: 31/12/2020 | E3: 31/12/2021 | F3: 31/12/2022 | G3: 31/12/2023 | H3: 31/12/2024 | I3: 31/03/2025 | J3: 30/06/2025 | K3: 30/09/2025 | L3: 30/09/2025
A4: 1122500 | B4: EFECTIVO Y EQUIVALENTES A EFECTIVO | C4: 9967093 | D4: 14545799 | E4: 19408214 | F4: 22691013 | G4: 93878129 | H4: 188260 | I4: 212097 | J4: 230814 | K4: 299173 | L4: =K4 -> 299173
A5: 1122300 | B5: ACTIVOS FINANCIEROS CORRIENTES | C5: 12819 | D5: 270000 | E5: 544078 | F5: 2039685 | G5: 0 | H5: 64173 | I5: 73996 | J5: 77183 | K5: 115489 | L5: =K5 -> 115489
A6: 1121999 | B6: CUENTAS POR COBRAR CORRIENTES | C6: 23395431 | D6: 31592147 | E6: 54532538 | F6: 104628601 | G6: 380795936 | H6: 591981 | I6: 736926 | J6: 773762 | K6: 852853 | L6: =K6 -> 852853
A7: 1122400 | B7: OTROS ACTIVOS NO FINANCIEROS CORRIENTES | C7: 436790 | D7: 722611 | E7: 1798310 | F7: 2860723 | G7: 92134890 | H7: 169750 | I7: 189906 | J7: 193607 | K7: 223489 | L7: =K7 -> 223489
A8: 1120100 | B8: INVENTARIOS CORRIENTES | C8: 21740320 | D8: 31360263 | E8: 55408397 | F8: 125775152 | G8: 430247953 | H8: 813051 | I8: 869479 | J8: 969144 | K8: 1046192 | L8: =K8 -> 1046192
A9: 1139999 | B9: ACTIVO CORRIENTE | C9: 55552453 | D9: 78490820 | E9: 131691537 | F9: 257995174 | G9: 997056908 | H9: 1827215 | I9: 2082404 | J9: 2244510 | K9: 2537196 | L9: =K9 -> 2537196
A10: 1112400 | B10: ACTIVOS FINANCIEROS NO CORRIENTES | C10: 0 | D10: 0 | E10: 0 | F10: 0 | G10: 25651862 | H10: 0 | I10: 0 | J10: 0 | K10: 0 | L10: =K10 -> 0
A11: 1111999 | B11: CUENTAS POR COBRAR NO CORRIENTES | C11: 2021473 | D11: 2871511 | E11: 5308379 | F11: 6869911 | G11: 33105015 | H11: 40525 | I11: 51263 | J11: 65626 | K11: 55038 | L11: =K11 -> 55038
A12: 1110100 | B12: PROPIEDADES PLANTAS Y EQUIPOS | C12: 36153579 | D12: 47341953 | E12: 69068934 | F12: 129208029 | G12: 448330019 | H12: 871537 | I12: 942319 | J12: 1040530 | K12: 1179900 | L12: =K12 -> 1179900
A13: 1112500 | B13: OTROS ACTIVOS NO FINANCIEROS NO CORRIENTES | C13: 11334032 | D13: 13956676 | E13: 20079742 | F13: 34882563 | G13: 114849968 | H13: 191735 | I13: 196849 | J13: 214940 | K13: 241236 | L13: =K13 -> 241236
A14: 1110200 | B14: ACTIVOS INTANGIBLES | C14: 6012614 | D14: 8047950 | E14: 12120352 | F14: 23760963 | G14: 74628912 | H14: 156774 | I14: 168364 | J14: 181856 | K14: 200346 | L14: =K14 -> 200346
A15: 1119999 | B15: ACTIVO NO CORRIENTE | C15: 55521698 | D15: 72218090 | E15: 106577407 | F15: 194721466 | G15: 696565776 | H15: 1260571 | I15: 1358795 | J15: 1502952 | K15: 1676520 | L15: =K15 -> 1676520
... A38: 2999999 | B38: TOTAL DEL PASIVO Y PATRIMONIO NETO | C38: 111074151 | D38: 150708910 | E38: 238268944 | F38: 452716640 | G38: 1693622684 | H38: 3087786 | I38: 3441199 | J38: 3747462 | K38: 4213716 | L38: =K38 -> 4213716
A39: 3000100 | B39: INGRESOS DE ACTIVIDADES ORDINARIAS | C39: 134710183 | D39: 177011474 | E39: 301186064 | F39: 625082119 | G39: 1915228985 | H39: 3939656 | I39: 1001485 | J39: 2141900 | K39: 3509495 | L39: =J39+K39 -> 5651395
A40: 3000200 | B40: COSTO DE VENTAS Y/O SERVICIOS | C40: -95708003 | D40: -118808429 | E40: -213122964 | F40: -441556114 | G40: -1376307150 | H40: -2798707 | I40: -701508 | J40: -1522399 | K40: -2472049 | L40: =J40+K40 -> -3994448
A41: 3009999 | B41: GANANCIA (PERDIDA) BRUTA | C41: 39002180 | D41: 58203045 | E41: 88063100 | F41: 183526005 | G41: 538921835 | H41: 1140949 | I41: 299977 | J41: 619501 | K41: 1037446 | L41: =J41+K41 -> 1656947
A42: 3011301 | B42: HONORARIOS A DIRECTORES Y SINDICOS | C42: -337237 | D42: -689261 | E42: -949583 | F42: -2006338 | G42: -4658927 | H42: -7044 | I42: -1999 | J42: -2805 | K42: -5249 | L42: =J42+K42 -> -8054
A43: 3011300 | B43: OTROS GASTOS DE ADMINISTRACION | C43: -5490776 | D43: -6652861 | E43: -11150213 | F43: -26983449 | G43: -89031509 | H43: -150930 | I43: -36714 | J43: -87183 | K43: -142918 | L43: =J43+K43 -> -230101
A44: 3011200 | B44: GASTOS DE COMERCIALIZACION Y/O DISTRIBUCION | C44: -22539035 | D44: -27089202 | E44: -44890744 | F44: -90240960 | G44: -286127543 | H44: -608210 | I44: -149571 | J44: -327305 | K44: -527364 | L44: =J44+K44 -> -854669
A45: 3011400 | B45: OTROS GASTOS OPERATIVOS | C45: 0 | D45: 0 | E45: 0 | F45: 0 | G45: 0 | H45: 0 | I45: 0 | J45: 0 | K45: 0 | L45: =J45+K45 -> 0
A46: 3011100 | B46: OTROS INGRESOS | C46: 413377 | D46: -550419 | E46: -911686 | F46: -5984624 | G46: -2542498 | H46: -57142 | I46: -5222 | J46: -14571 | K46: -23816 | L46: =J46+K46 -> -38387
A47: 3011600 | B47: DEPRECIACIONES Y AMORTIZACIONES | C47: -4498808 | D47: -5059685 | E47: -8113506 | F47: -15882085 | G47: -48388971 | H47: -108372 | I47: -26506 | J47: -60339 | K47: -100525 | L47: =J47+K47 -> -160864
A48: 3019999 | B48: GANANCIA (PERDIDA) DE ACTIVIDADES OPERATIVAS | C48: 6549701 | D48: 18161617 | E48: 22047368 | F48: 42428549 | G48: 108172387 | H48: 209251 | I48: 79965 | J48: 127298 | K48: 237574 | L48: =J48+K48 -> 364872
A49: 3021400 | B49: INGRESOS FINANCIEROS | C49: 405118 | D49: -1411174 | E49: -2162115 | F49: -13927463 | G49: -30087535 | H49: -83576 | I49: 7734 | J49: 7557 | K49: 14536 | L49: =J49+K49 -> 22093
A50: 3021500 | B50: COSTOS FINANCIEROS | C50: -4664315 | D50: -5511962 | E50: -2559124 | F50: -237389 | G50: 73098377 | H50: -75429 | I50: -27595 | J50: -64250 | K50: -98058 | L50: =J50+K50 -> -162308
... A63: 3240000 | B63: INCREMENTO (DISMINUCION) NETA DE EFECTIVO Y EQUIVALENTES | C63: 2905662 | D63: 877267 | E63: 1710708 | F63: -7365122 | G63: 12236298 | H63: 72610 | I63: 15582 | J63: 11202 | K63: 32193 | L63: =J63+K63 -> 43395
A64: 8000000 | B64: GANANCIA (PERDIDA) BASICA POR ACCION | C64: -0.02 | D64: 0.06 | E64: 0.26 | F64: 0.46 | G64: 0.07 | H64: 0 | I64: 0 | J64: 0 | K64: 0 | L64: =K64 -> 0
A65: 8000001 | B65: GANANCIAS (PERDIDA) DILUIDA POR ACCION | C65: -0.02 | D65: 0.06 | E65: 0.26 | F65: 0.46 | G65: 0.07 | H65: 0 | I65: 0 | J65: 0 | K65: 0 | L65: =K65 -> 0
A66: 8000002 | B66: TOTAL PATRIMONIO NETO DEL EJERCICIO ANTERIOR | C66: 31444737 | D66: 40720271 | E66: 65971538 | F66: 141917035 | G66: 489343074 | H66: 1226060 | I66: 1226828 | J66: 1321121 | K66: 1410449 | L66: =K66 -> 1410449
A67: 8000003 | B67: EBIT | C67: 6549701 | D67: 18161617 | E67: 22047368 | F67: 42428549 | G67: 108172387 | H67: 209251 | I67: 79965 | J67: 127298 | K67: 237574 | L67: =J67+K67 -> 364872
A68: 8000004 | B68: EBITDA | C68: 11048509 | D68: 23221302 | E68: 30160874 | F68: 59008392 | G68: 1.6815913e+08 | H68: 318358.24 | I68: 100270.01 | J68: 175682.46 | K68: 317882.77 | L68: =J68+K68 -> 493565.23
A69: 8000005 | B69: CAPITAL DE TRABAJO | C69: 16564312 | D69: 28175955 | E69: 46803876 | F69: 55710453 | G69: 285398020 | H69: 355316 | I69: 386731 | J69: 469833 | K69: 857035 | L69: =K69 -> 857035
A70: 8000006 | B70: LIQUIDEZ | C70: 1.42 | D70: 1.56 | E70: 1.55 | F70: 1.28 | G70: 1.4 | H70: 1.24 | I70: 1.23 | J70: 1.26 | K70: 1.51 | L70: =K70 -> 1.51
A71: 8000007 | B71: SOLVENCIA | C71: 0.37 | D71: 0.41 | E71: 0.44 | F71: 0.53 | G71: 0.5 | H71: 0.59 | I71: 0.58 | J71: 0.57 | K71: 0.57 | L71: =K71 -> 0.57
A72: 8000008 | B72: INMOVILIZACION DEL CAPITAL | C72: 0.5 | D72: 0.48 | E72: 0.45 | F72: 0.43 | G72: 0.41 | H72: 0.41 | I72: 0.39 | J72: 0.4 | K72: 0.4 | L72: =K72 -> 0.4
A73: 8000009 | B73: RENTABILIDAD PATRIMONIO NETO | C73: 0.1 | D73: 0.26 | E73: 0.5 | F73: 0.24 | G73: 0.05 | H73: 0.26 | I73: 0.04 | J73: 0.04 | K73: 0.07 | L73: =K73 -> 0.07
A74: 8000010 | B74: RENTABILIDAD DEL ACTIVO | C74: 0.03 | D74: 0.07 | E74: 0.14 | F74: 0.08 | G74: 0.02 | H74: 0.1 | I74: 0.01 | J74: 0.02 | K74: 0.02 | L74: =K74 -> 0.02
A75: 8000011 | B75: ENDEUDAMIENTO | C75: 2.71 | D75: 2.45 | E75: 2.27 | F75: 1.88 | G75: 2.01 | H75: 1.7 | I75: 1.73 | J75: 1.75 | K75: 1.75 | L75: =K75 -> 1.75
A76: 8000012 | B76: ENDEUDAMIENTO A CORTO PLAZO | C76: 1.3 | D76: 1.15 | E76: 1.17 | F76: 1.29 | G76: 1.26 | H76: 1.29 | I76: 1.34 | J76: 1.3 | K76: 1.1 | L76: =K76 -> 1.1
A77: 8000013 | B77: APALANCAMIENTO | C77: 3.71 | D77: 3.45 | E77: 3.27 | F77: 2.88 | G77: 3.01 | H77: 2.7 | I77: 2.73 | J77: 2.75 | K77: 2.75 | L77: =K77 -> 2.75
A78: 8000014 | B78: MARGEN NETO / VENTAS | C78: 0 | D78: 0.03 | E78: 0.02 | F78: 0.04 | G78: 0.07 | H78: -0.01 | I78: 0.05 | J78: 0.05 | K78: 0.05 | L78: =K78 -> 0.05
A79: 8000015 | B79: DEUDA FINANCIERA / EBITDA | C79: 4.91 | D79: 2.75 | E79: 2.83 | F79: 2.18 | G79: 3.09 | H79: 2.9 | I79: 10.58 | J79: 6.82 | K79: 4.33 | L79: =K79 -> 4.33
A80: 8000016 | B80: EBITDA / COSTOS FINANCIEROS | C80: -2.37 | D80: -4.21 | E80: -11.79 | F80: -248.57 | G80: 2.3 | H80: -4.22 | I80: -3.63 | J80: -2.73 | K80: -3.24 | L80: =K80 -> -3.24
A81: 8000017 | B81: ANALISIS DU-PONT | C81: 0.1 | D81: 0.25 | E81: 0.47 | F81: 0.23 | G81: 0.05 | H81: 0.27 | I81: 0.04 | J81: 0.04 | K81: 0.06 | L81: =K81 -> 0.06
A82: 8000027 | B82: PRUEBA ACIDA | C82: - | D82: - | E82: - | F82: 0.65 | G82: 0.8 | H82: 0.69 | I82: 0.72 | J82: 0.72 | K82: 0.89 | L82: =K82 -> 0.89
A83: 8000028 | B83: COBERTURA DE GASTOS FINANCIEROS | C83: - | D83: - | E83: - | F83: -178.73 | G83: 1.48 | H83: -2.77 | I83: -2.9 | J83: -1.98 | K83: -2.42 | L83: =K83 -> -2.42
A84: 8000029 | B84: ROTACION DE ACTIVOS | C84: - | D84: - | E84: - | F84: 1.38 | G84: 1.13 | H84: 1.28 | I84: 0.29 | J84: 0.57 | K84: 0.83 | L84: =K84 -> 0.83

Sheet cuadros
A1: AÑO | B1: TOTAL DEL ACTIVO | C1: RESULTADO DEL EJERCICIO
A2: 2019 | B2: $ 3.677.373,09 | C2: -$ 4.770,44
A3: 2020 | B3: $ 3.665.017,05 | C3: $ 132.337,28
A4: 2021 | B4: $ 3.838.799,81 | C4: $ 320.909,41
A5: 2022 | B5: $ 3.744.387,00 | C5: $ 292.628,51
A6: 2023 | B6: $ 4.498.230,08 | C6: $ 69.193,23
A7: 2024 | B7: $ 3.766.056,70 | C7: $ 376.808,62
A8: 2025-Q1 | B8: $ 3.865.833,58 | C8: $ 53.483,82
A9: 2025-H1 | B9: $ 3.971.120,60 | C9: $ 62.079,39
A10: 2025-Q3 | B10: $ 4.213.716,00 | C10: $ 97.772,00
A11: 2025 (ENE-SEP) | B11: $ 4.213.716,00 | C11: $ 156.355,00
A14: AÑO | B14: TOTAL DEL PAS | C14: TOTAL DEL ACTIVO
A15: 2019 | B15: $ 2.687.116,54 | C15: $ 3.677.373,09
A16: 2020 | B16: $ 2.602.136,03 | C16: $ 3.665.017,05
A17: 2021 | B17: $ 2.665.014,15 | C17: $ 3.838.799,81
A18: 2022 | B18: $ 2.444.700,93 | C18: $ 3.744.387,00
A19: 2023 | B19: $ 3.002.846,98 | C19: $ 4.498.230,08
A20: 2024 | B20: $ 2.369.954,20 | C20: $ 3.766.056,70
A21: 2025 (ENE-SEP) | B21: $ 2.682.999,00 | C21: $ 4.213.716,00
A23: AÑO | B23: ENDEUDAMIENTO | C23: SOLVENCIA
A24: 2019 | B24: 2.71 | C24: 0.37
A25: 2020 | B25: 2.45 | C25: 0.41
A26: 2021 | B26: 2.27 | C26: 0.44
A27: 2022 | B27: 1.88 | C27: 0.53
A28: 2023 | B28: 2.01 | C28: 0.5
A29: 2024 | B29: 1.7 | C29: 0.59
A30: 2025 | B30: 1.75 | C30: 0.57
A32: Período | B32: ENDEUDAMIENTO | C32: SOLVENCIA
A33: Pandemia | B33: 2.48 | C33: 0.41
A34: Recesion | B34: 1.86 | C34: 0.54
A37: graficos | B37: liquidez | C37: prueba acida
A38: 2019 | B38: 1.4248551 | C38: 0.86724148
A39: 2020 | B39: 1.5599927 | C39: 0.93671238
A40: 2021 | B40: 1.5513625 | C40: 0.89863638
A41: 2022 | B41: 1.2754061 | C41: 0.65363326
A42: 2023 | B42: 1.401032 | C42: 0.79646157
A43: 2024 | B43: 1.2413997 | C43: 0.68901739
A44: 2025 | B44: 1.510091 | C44: 0.88741734
A54: 2019 | B54: 548400.82
A55: 2020 | B55: 685197.41
A56: 2021 | B56: 754066.84
A57: 2022 | B57: 460777.18
A58: 2023 | B58: 758011.79
A59: 2024 | B59: 433365.59
A60: 2025 | B60: 857035
A68: 2019 | B68: 0.33615499
A69: 2020 | B69: 0.43132613
A70: 2021 | B70: 0.20468282
A71: 2022 | B71: 0.25461322
A72: 2023 | B72: 0.29406175
A73: 2024 | B73: 0.14579329
A74: 2025 | B74: 0.19865358
B80: ROA | C80: ROE
A81: 2019 | B81: -0.0012972415 | C81: -0.0048173789
A82: 2020 | B82: 0.03610823 | C82: 0.12450808
A83: 2021 | B83: 0.083596287 | C83: 0.27339694
A84: 2022 | B84: 0.078151247 | C84: 0.22515323
A85: 2023 | B85: 0.015382323 | C85: 0.046271238
A86: 2024 | B86: 0.10005389 | C86: 0.2699004
A87: 2025 | B87: 0.037106203 | C87: 0.10214494
B96: variacion ventas | C96: variacion utilidad bruta
A97: 2019 | B97: - | C97: -
A98: 2020 | B98: -0.034808761 | C98: 0.096148017
A99: 2021 | B99: 0.12726081 | C99: 0.002395752
A100: 2022 | B100: 0.065438657 | C100: 0.069867239
A101: 2023 | B101: -0.016092295 | C101: -0.057027776
A102: 2024 | B102: -0.055390619 | C102: -0.027801135
A103: 2025 | B103: 0.61031573 | C103: 0.59714048
B121: activos | C121: pasivos
A122: 2019 | B122: 1.2127951 | C122: 1.6597345
A123: 2020 | B123: 1.1745256 | C123: 1.654278
A124: 2021 | B124: 1.2640593 | C124: 1.8208048
A125: 2022 | B125: 1.3807359 | C125: 2.114782
A126: 2023 | B126: 1.1308475 | C126: 1.6939965
A127: 2024 | B127: 1.2758838 | C127: 2.0274867
A128: 2025 | B128: 1.3411903 | C128: 2.1063724
B137: ARCOR | C137: INDEC
A138: 2019 | B138: - | C138: -0.098
A139: 2020 | B139: -0.034808761 | C139: 0.008
A140: 2021 | B140: 0.12726081 | C140: 0.015
A141: 2022 | B141: 0.065438657 | C141: 0.016
A142: 2023 | B142: -0.016092295 | C142: 0.009
A143: 2024 | B143: -0.055390619 | C143: -0.11
A144: 2025 | B144: 0.61031573
B152: Actividad operativa | C152: Actividad de inversion | D152: Actividad de financiacion | E152: Variacion del Efectivo y equivalentes
A153: 2019 | B153: 433907.12 | C153: -118425.76 | D153: -219282.53 | E153: 96198.829
A154: 2020 | B154: 527763.26 | C154: -72068.36 | D154: -434361.06 | E154: 21333.832
A155: 2021 | B155: 279932.93 | C155: -97302.398 | D155: -155068.96 | E155: 27561.567
A156: 2022 | B156: 425988.92 | C156: -95049.602 | D156: -391855.71 | E156: -60916.398
A157: 2023 | B157: 555821.59 | C157: -303819.96 | D157: -219502.25 | E157: 32499.378
A158: 2024 | B158: 261731.03 | C158: -218185.42 | D158: 45014.083 | E158: 88559.692
A159: 2025 | B159: 333770 | C159: -191946 | D159: -98429 | E159: 43395
A183: 2019 | B183: -0.022573286
A184: 2020 | B184: 0.70095948
A185: 2021 | B185: 5.4034004
A186: 2022 | B186: 97.307606
A187: 2023 | B187: -0.23791531
A188: 2024 | B188: 2.5774837
A189: 2025 | B189: 0.61337645
A199: Tabla de Rentabilidad
...

Sheet ipc empalme ipim
A1: RESOLUCIÓN TÉCNICA N° 6 "ESTADOS CONTABLES EN MONEDA HOMOGENEA" ÍNDICE DEFINIDO POR LA RESOLUCIÓN DE JG 539/18
A3: MES | B3: IPC NACIONAL EMPALME IPIM
A4: 33970 | B4: 7.4670667
A5: 34001 | B5: 7.5009994
A6: 34029 | B6: 7.5228554
A7: 34060 | B7: 7.5619708
A8: 34090 | B8: 7.5379825
A9: 34121 | B9: 7.5522869
A10: 34151 | B10: 7.5600077
A11: 34182 | B11: 7.5932269
A12: 34213 | B12: 7.5641673
A13: 34243 | B13: 7.5769305
A14: 34274 | B14: 7.5110624
A15: 34304 | B15: 7.4488594
... A402: 46082 | B402: 11077.061
A403: 46113 | B403: *
A405: * Teniendo en cuenta el Calendario de difusión que publica el INDEC en su página WEB, el Índice de precios al consumidor con cobertura nacional del mes de abril/26 , será públicado en la Web de FACPCE el día 15/05/2026.
